pip_upgrade/__init__.py
pip_upgrade/__main__.py
pip_upgrade/cache.py
pip_upgrade/dependencies_base.py
pip_upgrade/dev.py
pip_upgrade/main.py
pip_upgrade/store.py
pip_upgrade/tool.py
pip_upgrade/version_checker.py
pip_upgrade/packages/__init__.py
pip_upgrade/packages/package.py
pip_upgrade/packages/package_set.py
pip_upgrade/repositories/pypi_repository.py
pip_upgrade/solver/solver.py
pip_upgrade/tools/__init__.py
pip_upgrade/tools/clear_cache.py
pip_upgrade/tools/config.py
pip_upgrade/tools/cprint.py
pip_upgrade_tool-1.1.0.dist-info/METADATA
pip_upgrade_tool-1.1.0.dist-info/WHEEL
pip_upgrade_tool-1.1.0.dist-info/entry_points.txt
pip_upgrade_tool-1.1.0.dist-info/licenses/LICENSE
pip_upgrade_tool-1.1.0.dist-info/RECORD
