Metadata-Version: 2.4
Name: pip-upgrade-tool
Version: 1.1.0
Summary: An easy tool for upgrading all of your packages while not breaking dependencies
Project-URL: Homepage, https://github.com/realiti4/pip-upgrade
Author-email: Onur Cetinkol <onurcetinkol@gmail.com>
License-File: LICENSE
Classifier: License :: OSI Approved :: MIT License
Classifier: Operating System :: OS Independent
Classifier: Programming Language :: Python :: 3
Requires-Python: >=3.11
Requires-Dist: packaging
